wf/__init__.py
wf-0.0.4.dist-info/DESCRIPTION.rst
wf-0.0.4.dist-info/METADATA
wf-0.0.4.dist-info/RECORD
wf-0.0.4.dist-info/WHEEL
wf-0.0.4.dist-info/metadata.json
wf-0.0.4.dist-info/top_level.txt
