Metadata-Version: 2.0
Name: wf
Version: 0.0.4
Summary: wf
Home-page: UNKNOWN
Author: UNKNOWN
Author-email: UNKNOWN
License: GPLv2+
Platform: UNKNOWN
Classifier: Development Status :: 3 - Alpha
Classifier: License :: OSI Approved :: GNU General Public License v2 or later (GPLv2+)
Classifier: Intended Audience :: Developers
Classifier: Programming Language :: Python :: 3.6
Classifier: Programming Language :: Python :: 3.7
